{
  "dataset": "eegmat",
  "n_train": 1555,
  "n_test": 470,
  "n_subjects": 36,
  "models": {
    "GCN": {
      "accuracy": 0.7362,
      "f1": 0.6936,
      "precision": 0.6829,
      "recall": 0.7362,
      "auc": 0.5497
    },
    "GAT": {
      "accuracy": 0.7255,
      "f1": 0.6952,
      "precision": 0.6824,
      "recall": 0.7255,
      "auc": 0.5538
    },
    "LogisticRegression": {
      "accuracy": 0.6319,
      "f1": 0.6582,
      "auc": 0.7293
    },
    "RandomForest": {
      "accuracy": 0.7213,
      "f1": 0.6887,
      "auc": 0.6704
    }
  },
  "electrode_importance": {
    "Fp1": 1.0,
    "Fp2": 1.0,
    "F3": 1.0,
    "F4": 1.0,
    "C3": 1.0,
    "C4": 1.0,
    "P3": 1.0,
    "P4": 1.0,
    "O1": 1.0,
    "O2": 1.0,
    "F7": 1.0,
    "F8": 1.0,
    "T3": 1.0,
    "T4": 1.0,
    "T5": 1.0,
    "T6": 1.0,
    "Fz": 1.0,
    "Cz": 1.0,
    "Pz": 1.0
  },
  "top_electrodes": [
    "Fp2",
    "Fz",
    "Fp1",
    "F3",
    "P4"
  ]
}